common/__init__.py
common/critical_graph_utils.py
common/critical_point.py
common/decorator.py
common/graph_utils.py
common/params.py
common/model/__init__.py
common/model/dlq.py
common/model/enums.py
common/model/half_plane.py
common/model/length_comparison_result.py
common/model/point.py
common/model/vector.py
common/traversal/__init__.py
common/traversal/graph_traversal.py
common/traversal/start_point_selector.py
common/traversal/visitors/__init__.py
common/traversal/visitors/angle_visitor.py
common/traversal/visitors/direction_visitor.py
common/traversal/visitors/length_comparison_visitor.py
common/traversal/visitors/quadrant_visitor.py
common/traversal/visitors/visitor.py
common/traversal/visitors/visitor_result_persistence_service.py
natural_agi-0.1.39.dist-info/METADATA
natural_agi-0.1.39.dist-info/WHEEL
natural_agi-0.1.39.dist-info/top_level.txt
natural_agi-0.1.39.dist-info/RECORD
