Metadata-Version: 2.4
Name: natural-agi
Version: 0.1.39
Summary: Components of reduction neural networks concept
Author-email: koboh <konstboh@gmail.com>, nlapin <nlapin.java@gmail.com>
Requires-Python: >=3.12
Requires-Dist: neo4j>=5.13.0
Requires-Dist: opencv-python>=4.8.1
Requires-Dist: pillow>=10.0.1
Requires-Dist: pydantic>=2.4.2
Requires-Dist: pydantic-settings>=2.0.0
Requires-Dist: requests>=2.31.0
Requires-Dist: networkx>=3.0
Requires-Dist: numpy>=1.26.0
Requires-Dist: scipy>=1.11.0
Requires-Dist: scikit-image>=0.22.0
Requires-Dist: scikit-learn>=1.3.2
Requires-Dist: matplotlib>=3.8.1
Requires-Dist: kafka-python>=2.0.0
Requires-Dist: nuclio-sdk>=0.5.6
Requires-Dist: msgpack>=1.0.0
Requires-Dist: rdp>=0.8
Requires-Dist: skan>=0.11.0
Requires-Dist: ypstruct>=0.0.2
Requires-Dist: tqdm>=4.66.0
Provides-Extra: dev
Requires-Dist: notebook>=7.0.4; extra == "dev"
Requires-Dist: ipywidgets>=8.0.0; extra == "dev"
Requires-Dist: seaborn>=0.13.0; extra == "dev"
Requires-Dist: python-dotenv>=1.0.0; extra == "dev"
Requires-Dist: bibtexparser>=1.4.0; extra == "dev"
Requires-Dist: pyvis>=0.3.0; extra == "dev"
Provides-Extra: ml
Requires-Dist: torch>=2.0.0; extra == "ml"
Requires-Dist: torchvision>=0.15.0; extra == "ml"
Requires-Dist: torch-geometric>=2.4.0; extra == "ml"
Requires-Dist: grakel>=0.1.10; extra == "ml"
Requires-Dist: gspan-mining>=0.2.0; extra == "ml"
Requires-Dist: pandas>=2.0.0; extra == "ml"
